repos.py
student_repos_handler-1.1.0.dist-info/LICENSE
student_repos_handler-1.1.0.dist-info/METADATA
student_repos_handler-1.1.0.dist-info/WHEEL
student_repos_handler-1.1.0.dist-info/entry_points.txt
student_repos_handler-1.1.0.dist-info/top_level.txt
student_repos_handler-1.1.0.dist-info/RECORD
